LICENSE
MANIFEST.in
README.rst
helga_yelling.py
setup.py
helga_yelling.egg-info/PKG-INFO
helga_yelling.egg-info/SOURCES.txt
helga_yelling.egg-info/dependency_links.txt
helga_yelling.egg-info/entry_points.txt
helga_yelling.egg-info/top_level.txt
helga_yelling.egg-info/zip-safe